pagestream/__init__.py
pagestream/cli.py
pagestream-0.2.5.dist-info/entry_points.txt
pagestream-0.2.5.dist-info/LICENSE
pagestream-0.2.5.dist-info/WHEEL
pagestream-0.2.5.dist-info/METADATA
pagestream-0.2.5.dist-info/RECORD
