Metadata-Version: 2.1
Name: pagestream
Version: 0.2.5
Summary: Handle PDF pagestreams with PikePDF and split them by outline
Author-email: Johan Schuijt <johan@ftm.nl>
Classifier: License :: OSI Approved :: MIT License
Requires-Dist: pikepdf
Requires-Dist: click
Project-URL: Home, https://github.com/followthemoney/pagestream
